py_tldr/__init__.py
py_tldr/core.py
py_tldr/page.py
py_tldr/parse.py
py_tldr-0.9.0.dist-info/METADATA
py_tldr-0.9.0.dist-info/WHEEL
py_tldr-0.9.0.dist-info/entry_points.txt
py_tldr-0.9.0.dist-info/top_level.txt
py_tldr-0.9.0.dist-info/RECORD
