Metadata-Version: 2.1
Name: py-tldr
Version: 0.9.0
Summary: New Python client for tldr pages
Author-email: iamgodot <xugodot@gmail.com>
License: MIT
Project-URL: Issue Tracker, https://github.com/iamgodot/py-tldr/issues
Classifier: Development Status :: 3 - Alpha
Classifier: Intended Audience :: Developers
Classifier: License :: OSI Approved :: MIT License
Classifier: Operating System :: OS Independent
Classifier: Programming Language :: Python
Requires-Python: >=3.7
Requires-Dist: click (==8.0.3)
Requires-Dist: toml (==0.10.2)
Requires-Dist: requests (==2.26.0)
Requires-Dist: yaspin (==2.1.0)
